beyonddesk_grpc/__init__.py
beyonddesk_grpc/user_service/__init__.py
beyonddesk_grpc/user_service/user_service_pb2.py
beyonddesk_grpc/user_service/user_service_pb2_grpc.py
beyonddesk_grpc_protocols-0.1.5.dist-info/METADATA
beyonddesk_grpc_protocols-0.1.5.dist-info/WHEEL
beyonddesk_grpc_protocols-0.1.5.dist-info/top_level.txt
beyonddesk_grpc_protocols-0.1.5.dist-info/RECORD
